[1,0,0,[["cc.JsonAsset",["_name","json"],1]],[[0,0,1,3]],[[0,"ItemData",[{"id":0,"icon":"item_1","value":[{"type":"Red","value":1},{"type":"Blue","value":1},{"type":"Weed","value":1}]},{"id":1,"icon":"item_1","value":[{"type":"Red","value":1},{"type":"Blue","value":1},{"type":"Weed","value":1}]},{"id":2,"icon":"item_2","value":[{"type":"Sugar","value":3}]},{"id":3,"icon":"item_3","value":[{"type":"Sugar","value":1},{"type":"Flour","value":1},{"type":"Blue","value":1}]},{"id":4,"icon":"item_4","value":[{"type":"Sugar","value":1},{"type":"Flour","value":1},{"type":"Red","value":1}]},{"id":5,"icon":"item_29","value":[{"type":"Flour","value":2},{"type":"Sugar","value":1}]},{"id":6,"icon":"item_6","value":[{"type":"Sugar","value":1},{"type":"Blue","value":1},{"type":"Weed","value":1}]},{"id":7,"icon":"item_7","value":[{"type":"Flour","value":2},{"type":"Red","value":1}]},{"id":8,"icon":"item_8","value":[{"type":"Red","value":1},{"type":"Flour","value":2}]},{"id":9,"icon":"item_9","value":[{"type":"Flour","value":2},{"type":"Green","value":1}]},{"id":10,"icon":"item_33","value":[{"type":"Flour","value":3}]},{"id":11,"icon":"item_18","value":[{"type":"Tool","value":2}]},{"id":12,"icon":"item_23","value":[{"type":"Sex","value":1},{"type":"Red","value":1}]},{"id":13,"icon":"item_24","value":[{"type":"Sugar","value":1},{"type":"Glass","value":1}]},{"id":14,"icon":"item_25","value":[{"type":"Sex","value":1},{"type":"Green","value":1},{"type":"Weed","value":1}]},{"id":15,"icon":"item_50","value":[{"type":"Sex","value":1},{"type":"Weed","value":1}]},{"id":16,"icon":"item_28","value":[{"type":"Flour","value":2},{"type":"Weed","value":1}]},{"id":17,"icon":"item_10","value":[{"type":"Glass","value":1},{"type":"Blue","value":1},{"type":"Weed","value":1}]},{"id":18,"icon":"item_34","value":[{"type":"Tool","value":2}]},{"id":19,"icon":"item_36","value":[{"type":"Glass","value":1}]},{"id":20,"icon":"item_37","value":[{"type":"Glass","value":2},{"type":"Sex","value":1}]},{"id":21,"icon":"item_38","value":[{"type":"Tool","value":1},{"type":"Sex","value":1}]},{"id":22,"icon":"item_42","value":[{"type":"Glass","value":1},{"type":"Blue","value":1}]},{"id":23,"icon":"item_56","value":[{"type":"Sugar","value":1},{"type":"Sex","value":1},{"type":"Red","value":1}]},{"id":24,"icon":"item_46","value":[{"type":"Tool","value":1},{"type":"Blue","value":1}]},{"id":25,"icon":"item_47","value":[{"type":"Sex","value":2},{"type":"Weed","value":1}]},{"id":26,"icon":"item_58","value":[{"type":"Tool","value":1},{"type":"Weed","value":1}]},{"id":27,"icon":"item_49","value":[{"type":"Sex","value":1},{"type":"Weed","value":1}]}]]],0,0,[],[],[]]
